dxd/__about__.py
dxd/__init__.py
dxd/column.py
dxd/engine.py
dxd/expr.py
dxd/kvstore.py
dxd/pattern.py
dxd/postgres_engine.py
dxd/sqlite_engine.py
dxd/table.py
dxd-0.0.5.dist-info/METADATA
dxd-0.0.5.dist-info/WHEEL
dxd-0.0.5.dist-info/licenses/LICENSE.txt
dxd-0.0.5.dist-info/RECORD
