Metadata-Version: 2.1
Name: dxd
Version: 0.0.5
Project-URL: Documentation, https://github.com/EdAyers/sss/dxd#readme
Project-URL: Issues, https://github.com/EdAyers/sss/dxd/issues
Project-URL: Source, https://github.com/EdAyers/sss/dxd
Author-email: "E.W.Ayers" <contact@edayers.com>
License-Expression: MIT
License-File: LICENSE.txt
Classifier: Development Status :: 4 - Beta
Classifier: Programming Language :: Python
Classifier: Programming Language :: Python :: 3.9
Classifier: Programming Language :: Python :: 3.10
Classifier: Programming Language :: Python :: 3.11
Classifier: Programming Language :: Python :: Implementation :: CPython
Classifier: Programming Language :: Python :: Implementation :: PyPy
Requires-Python: >=3.9
Requires-Dist: miniscutil
